{
    "harry": "harry",
    "potter": "potter",
    "nao": "not",
    "faz": "make",
    "sentido": "sense",
    "nenhum": "none",
    "amo": "love",
    "fosse": "was",
    "realmente": "really",
    "fazer": "do",
    "analise": "analysis",
    "critica": "criticism",
    "livro": "book",
    "ia": "would",
    "acabar": "end",
    "pensando": "thinking",
    "mulher": "woman",
    "fumou": "smoked",
    "hora": "hour",
    "escrever": "write",
    "ja": "already",
    "carinho": "affection",
    "saga": "saga",
    "entao": "then",
    "todo": "all",
    "mundo": "world",
    "conhece": "knows",
    "historia": "story",
    "voce": "you",
    "sai": "leave",
    "caverna": "cave",
    "vai": "will",
    "saber": "know",
    "vou": "will",
    "resumir": "summarize",
    "crianca": "child",
    "igual": "like",
    "todas": "all",
    "criancas": "children",
    "tirando": "except",
    "parte": "part",
    "uns": "some",
    "tios": "uncles",
    "insuportaveis": "unbearable",
    "sao": "are",
    "imbecis": "idiots",
    "primo": "cousin",
    "pior": "worse",
    "ainda": "still",
    "ah": "ah",
    "um": "a",
    "bruxo": "wizard",
    "claro": "clear",
    "contraria": "contrary",
    "frase": "sentence",
    "comeco": "beginning",
    "gigante": "giant",
    "super": "super",
    "legal": "cool",
    "chamado": "called",
    "hagrid": "Hagrid",
    "sequestracofcof": "kidnappingcofcof",
    "perdao": "forgiveness",
    "leva": "takes",
    "ele": "he",
    "pra": "to",
    "escola": "school",
    "magia": "magic",
    "bruxaria": "witchcraft",
    "famosa": "famous",
    "hogwarts": "Hogwarts",
    "la": "there",
    "separados": "separated",
    "casas": "houses",
    "sei": "know",
    "tambem": "also",
    "grifinoria": "Gryffindor",
    "casa": "house",
    "chatos": "annoying",
    "preferidos": "favorites",
    "porque": "because",
    "lufa": "Hufflepuff",
    "maconheiros": "stoners",
    "corvinal": "Ravenclaw",
    "nerdola": "nerd",
    "esquisitos": "weirdos",
    "sonserina": "Slytherin",
    "projetinhos": "projects",
    "hitler": "Hitler",
    "gente": "people",
    "joga": "play",
    "jogo": "game",
    "bicho": "creature",
    "segura": "hold",
    "precisa": "needs",
    "preocupar": "worry",
    "talvez": "maybe",
    "filho": "son",
    "volte": "returns",
    "uma": "a",
    "corpo": "body",
    "algo": "something",
    "tipo": "type",
    "morto": "dead",
    "enfim": "finally",
    "vira": "becomes",
    "amigo": "friend",
    "pobre": "poor",
    "bruxa": "witch",
    "metida": "snobbish",
    "porem": "however",
    "inteligente": "smart",
    "vive": "lives",
    "altas": "high",
    "loucuras": "craziness",
    "doideras": "madness",
    "definitivamente": "definitely",
    "deveriam": "should",
    "acontecer": "happen",
    "vamos": "let's",
    "lembra": "remember",
    "disse": "said",
    "se": "if",
    "eu": "I",
    "analisar": "analyze",
    "pessoa": "person",
    "que": "that",
    "a": "the",
    "jk": "JK",
    "fuma": "smokes",
    "umas": "some",
    "adulto": "adult",
    "quiser": "wants",
    "ler": "read",
    "leia": "read",
    "ache": "find",
    "ridiculo": "ridiculous",
    "sem": "without",
    "acho": "think",
    "divertido": "funny",
    "gosto": "like",
    "escrita": "writing",
    "funciona": "works",
    "mim": "for me",
    "leve": "light",
    "fluida": "fluid",
    "acontecimentos": "events",
    "jogos": "games",
    "de": "of",
    "quadribol": "Quidditch",
    "aulas": "classes",
    "citadas": "mentioned",
    "aleatoriamente": "randomly",
    "sim": "yes",
    "recomendo": "recommend",
    "melhor": "better",
    "filme": "movie",
    "obvio": "obvious",
    "o": "the",
    "bem": "well",
    "mais": "more",
    "furos": "plot holes",
    "infelizmente": "unfortunately",
    "chatissima": "boring",
    "otimo": "great",
    "sensacao": "feeling",
    "nostalgia": "nostalgia",
    "causa": "causes",
    "lendo": "reading",
    "conhecer": "know",
    "filmes": "movies",
    "sensacional": "sensational",
    "leitura": "reading",
    "confortavel": "comfortable",
    "liderando": "leading",
    "elfos": "elves",
    "batalha": "battle",
    "final": "final",
    "kk": "kk",
    "diria": "would say",
    "tornaria": "would return",
    "perdas": "losses",
    "nesse": "in this",
    "ultimo": "last",
    "fred": "fred",
    "lupin": "lupine",
    "tonks": "tonks",
    "dobby": "dobby",
    "moody": "moody",
    "snape": "snap",
    "triste": "sad",
    "poderiam": "could",
    "levado": "taken",
    "umbridge": "umbridge",
    "lugar": "place",
    "estrelas": "stars",
    "deixou": "left",
    "mencionar": "mention",
    "dumbledore": "dumbledore",
    "grindelwald": "grindelwald",
    "foi": "was",
    "suma": "sum",
    "importancia": "importance",
    "objetos": "objects",
    "escolhidos": "chosen",
    "serem": "to be",
    "horcruxes": "horcruxes",
    "faltou": "missed",
    "nos": "us",
    "muitas": "many",
    "cenas": "scenes",
    "muitos": "many",
    "boas": "good",
    "aberforth": "aberforth",
    "soltando": "dropping",
    "patrono": "patron",
    "dispersando": "dispersing",
    "dementadores": "Dementors",
    "outras": "other",
    "desfecho": "end",
    "alguns": "some",
    "percy": "percy",
    "no": "no",
    "quase": "almost",
    "mencionado": "mentioned",
    "das": "das",
    "melhores": "best",
    "sagas": "sagas",
    "enorme": "huge",
    "prazer": "pleasure",
    "autora": "author",
    "nunca": "never",
    "esquecer": "forget",
    "meu": "my",
    "coracao": "heart",
    "serie": "series",
    "reliquias": "relics",
    "morte": "death",
    "aparicao": "appearance",
    "artefatos": "artifacts",
    "criaturas": "creatures",
    "proporciona": "provides",
    "leitor": "reader",
    "experiencia": "experience",
    "detalhada": "detailed",
    "dentro": "in",
    "principalmente": "mainly",
    "rica": "rich",
    "descricao": "description",
    "dada": "given",
    "longo": "long",
    "narrativa": "narrative",
    "intenso": "intense",
    "trata": "treats",
    "licoes": "lessons",
    "marcante": "striking",
    "fala": "speech",
    "enredo": "plot",
    "dois": "two",
    "adiando": "postponing",
    "sofrimento": "suffering",
    "fim": "end",
    "titulo": "title",
    "desta": "this",
    "breve": "brief",
    "resenha": "review",
    "diz": "says",
    "respeito": "respect",
    "atmosfera": "atmosphere",
    "sombria": "dark",
    "pesado": "heavy",
    "sabendo": "knowing",
    "feliz": "happy",
    "satisfatorio": "satisfactory",
    "pois": "because",
    "venceu": "won",
    "adiei": "postponed",
    "finalizacao": "finalization",
    "terminava": "ended",
    "logo": "logo",
    "viagem": "trip",
    "magico": "magic",
    "estendia": "extended",
    "pouco": "little",
    "ao": "ao",
    "diminuir": "decrease",
    "ritmo": "rhythm",
    "compartilhar": "share",
    "instagram": "instagram",
    "caduquelendo": "expiring",
    "sombrio": "dark",
    "desenrolou": "unrolled",
    "magistralmente": "masterfully",
    "crescia": "grew",
    "niveis": "levels",
    "fantasticos": "fantastic",
    "evolucao": "evolution",
    "varios": "various",
    "elementos": "elements",
    "valor": "value",
    "precedentes": "precedents",
    "conflito": "conflict",
    "menino": "boy",
    "sobreviveu": "survived",
    "enfrentar": "face",
    "alem": "beyond",
    "apego": "attachment",
    "emocional": "emotional",
    "criamos": "we created",
    "so": "so",
    "bruxos": "witches",
    "propria": "own",
    "marcou": "scored",
    "minha": "my",
    "infancia": "childhood",
    "companheiro": "companion",
    "durante": "during",
    "longos": "long",
    "anos": "years",
    "encerra": "closes",
    "ciclo": "cycle",
    "junto": "together",
    "comigo": "with me",
    "poderia": "could",
    "grata": "grateful",
    "geracoes": "generations",
    "marotos": "marauders",
    "perfeitos": "perfect",
    "meio": "middle",
    "ver": "see",
    "aluna": "student",
    "sendo": "being",
    "use": "use",
    "ela": "her",
    "nem": "neither",
    "usou": "used",
    "vida": "life",
    "bicuso": "bicuso",
    "prisioneiro": "prisoner",
    "azkaban": "azkaban",
    "fato": "fact",
    "encontrar": "find",
    "pessoas": "people",
    "gostem": "like",
    "apoiem": "support",
    "tem": "has",
    "riqueza": "wealth",
    "profunda": "deep",
    "apaixonante": "passionate",
    "sinto": "I feel",
    "emocoes": "emotions",
    "forma": "shape",
    "tudo": "all",
    "esclarece": "clarifies",
    "como": "like",
    "visto": "seen",
    "conhecia": "knew",
    "spoilers": "spoilers",
    "isso": "it",
    "tirou": "took",
    "dos": "dos",
    "li": "li",
    "terceiro": "third",
    "estou": "am",
    "impressionante": "impressive",
    "releitura": "reread",
    "consegue": "can",
    "nova": "new",
    "conectam": "connect",
    "coerente": "coherent",
    "reassistir": "rewatch",
    "ilha": "island",
    "medo": "fear",
    "engracado": "funny",